{
 "actions": [],
 "allow_rename": 1,
 "creation": "2025-03-25 17:23:10.339080",
 "doctype": "DocType",
 "engine": "InnoDB",
 "field_order": [
  "type_section",
  "naming_series",
  "title",
  "material_request_type",
  "customer",
  "company",
  "column_break_2",
  "transaction_date",
  "schedule_date",
  "amended_from",
  "custom_reason_for_rejection",
  "warehouse_section",
  "scan_barcode",
  "column_break_13",
  "set_from_warehouse",
  "set_warehouse",
  "items_section",
  "items",
  "items_tab",
  "terms_section_break",
  "tc_name",
  "more_info_tab",
  "status_section",
  "status",
  "per_ordered",
  "column_break2",
  "transfer_status",
  "per_received",
  "printing_details",
  "letter_head",
  "column_break_31",
  "select_print_heading",
  "reference",
  "job_card",
  "column_break_35",
  "work_order",
  "connections_tab",
  "custom_user_info",
  "custom_project_manager",
  "custom_project_manager_id",
  "custom_bu_head",
  "custom_bu_head_id",
  "custom_purchase_manager",
  "custom_purchase_manager_id",
  "column_break_5"
 ],
 "fields": [
  {
    "fieldname":"type_section",
    "fieldtype": "Section Break",
    "options": "fa fa-pushpin"
  },
  {
    "fieldname": "naming_series",
    "fieldtype": "Select",
    "label": "Series",
    "reqd": "1",
    "no_copy": "1",
    "default": "MR-.MM.-.YY.-.#####",
    "options": "MR-.MM.-.YY.-.#####\nMAT-MR-.YYYY.-",
    "print_hide": "1"
  },
  {
    "fieldname": "title",
    "fieldtype": "Data",
    "label": "Title",
    "default": "material_request_type",
    "no_copy": "1",
    "allow_on_sumit": "1",
    "hidden": "1",
    "print_hide": "1"
  },
  {
    "fieldname" : "material_request_type",
    "fieldtype" : "Select",
    "label": "Purpose",
    "reqd": "1",
    "in_list_view": "1",
    "in_standard_filter": "1",
    "options": "Purchase\nMaterial Transfer\nMaterial Issue\nManufacture\nCustomer Provided"
  },
  {
    "fieldname" :"customer",
    "fieldtype" :"Link",
    "label": "Customer",
    "options": "Customer",
    "print_hide": "1",
    "depends_on": "eval:doc.material_request_type == \"Customer Provided\""
  },
  {
    "fieldname" :"company",
    "fieldtype" : "Link",
    "label": "Company",
    "reqd": "1",
    "in_standard_filter": "1",
    "options": "Company",
    "remember_last_selected_value": "1",
    "print_hide": "1",
    "print_width": "150px",
    "width": "150px"
  },
  {
    "fieldname" :"column_break_2",
    "fieldtype" :"Column Break"
  },
  {
    "fieldname" :"transaction_date",
    "fieldtype" : "Date",
    "label": "Transaction Date",
    "reqd": "1",
    "no_copy": "1",
    "default": "Today",
    "print_width": "100px",
    "width": "100px"
  },
  {
    "fieldname" :"schedule_date",
    "fieldtype" : "Date",
    "label": "Required By",
    "in_list_view": "1",
    "allow_on_submit": "1"
  },
  {
    "fieldname" :"amended_from",
    "fieldtype" : "Link",
    "label": "Amended From",
    "options": "Material Request",
    "no_copy": "1",
    "ignore_user_permissions": "1",
    "read_only": "1",
    "print_hide": "1",
    "print_width": "150px",
    "width": "150px"

  },
  {
    "fieldname" :"custom_reason_for_rejection",
    "fieldtype" : "Small Text",
    "label": "Reason For Rejection",
    "translatable": "1"
  },
  {
    "fieldname" :"warehouse_section",
    "fieldtype" : "Section Break",
    "label": "Items",
    "hide_border": "1"
  },
  {
    "fieldname" :"scan_barcode",
    "fieldtype" : "Data",
    "label": "Scan Barcode",
    "options": "Barcode"
  },
  {
    "fieldname" :"column_break_13",
    "fieldtype" : "Column Break"
  },
  {
    "fieldname" :"set_from_warehouse",
    "fieldtype" : "Link",
    "label": "Set Source Warehouse",
    "options": "Warehouse",
    "ignore_user_permissions": "1",
    "depends_on": "eval:doc.material_request_type == \"Material Transfer\""
  },
  {
    "fieldname" :"set_warehouse",
    "fieldtype" : "Link",
    "label": "Set Target Warehouse",
    "options": "Warehouse",
    "in_list_view": "1",
    "ignore_user_permissions": "1"
  },
  {
    "fieldname": "items_section",
    "fieldtype": "Section Break",
    "options": "fa fa-shopping-cart"

  },
  {
    "fieldname": "items",
    "fieldtype": "Table",
    "label": "Items",
    "options": "Material Request Item",
    "reqd": "1",
    "allow_bulk_edit": "1"
  },
  {
    "fieldname": "terms_tab",
    "fieldtype": "Tab Break",
    "label": "Terms"
  },
  {
    "fieldname": "terms_section_break",
    "fieldtype": "Section Break",
    "label": "Terms",
    "options": "fa fa-legal",
    "collapsible": "1",
    "collapsible_depends_on": "terms"
  },
  {
    "fieldname": "tc_name",
    "fieldtype": "Link",
    "label": "Terms and Conditions",
    "options": "Terms and Conditions",
    "report_hide": "1",
    "print_hide": "1"
  },
  {
    "fieldname": "more_info_tab",
    "fieldtype": "Tab Break",
    "label": "More Info"
  },
  {
    "fieldname": "status_section",
    "fieldtype": "Section Break",
    "label": "Status",
    "icon": "fa fa-file-text"
  },
  {
    "fieldname": "status",
    "fieldtype": "Select",
    "label": "Status",
    "options": "Draft"
  },
  {
    "fieldname": "per_ordered",
    "fieldtype": "Percent",
    "label": "% Ordered"
  },
  {
    "fieldname": "column_break2",
    "fieldtype": "Column Break"
  },
  {
    "fieldname": "transfer_status",
    "fieldtype": "Select",
    "label": "Transfer Status",
    "options": "Not Started\nIn Transit\nCompleted",
    "allow_on_submit": "1",
    "read_only": "1",
    "depends_on": "eval:doc.add_to_transit == 1"
  },
  {
    "fieldname": "per_received",
    "fieldtype": "Percent",
    "label": "% Received",
    "no_copy": "1", 
    "depends_on": "eval:doc.per_received > 0",
    "read_only": "1",
    "print_hide": "1"
  },
  {
    "fieldname": "printing_details",
    "fieldtype": "Section Break",
    "label": "Printing Details",
    "collapsible": "1"
  },
  {
    "fieldname": "letter_head",
    "fieldtype": "Link",
    "label": "Letter Head",
    "options": "Letter Head",
    "allow_on_submit": "1",
    "print_hide": "1"
  },
  {
    "fieldname": "column_break_31",
    "fieldtype": "Column Break"
  },
  {
    "fieldname": "select_print_heading",
    "fieldtype": "Link",
    "label": "Print Heading",
    "options": "Print Heading",
    "allow_on_sumit": "1",
    "print_hide": "1"
  },
  {
    "fieldname": "reference",
    "fieldtype": "Section Break",
    "label": "Reference",
    "collapsible": "1"
  },
  {
    "fieldname": "job_card",
    "fieldtype": "Link",
    "label": "Job Card",
    "options": "Job Card",
    "read_only": "1"
  },
  {
    "fieldname" :"column_break_35",
    "fieldtype" : "Column Break"
  },
  {
    "fieldname" :"work_order",
    "fieldtype" :"Link",
    "label": "Work Order",
    "options": "Work Order",
    "read_only": "1"
  },
  {
    "fieldname" :"connections_tab",
    "fieldtype" : "Tab Break",
    "label": "Connections",
    "show_dashboard": "1"
  },
  {
    "fieldname" :"custom_user_info",
    "fieldtype" : "Section Break",
    "label": "User Info"
  },
  {
    "fieldname" :"custom_project_manager",
    "fieldtype" : "Link",
    "label": "Project Manager",
    "options": "Employee",
    "ignore_user_permissions": "1",
    "read_only": "1",
    "depends_on": "eval:doc.workflow_state == \"Draft\""
  },
  {
    "fetch_from": "custom_project_manager.user_id",
    "fieldname" :"custom_project_manager_id",
    "fieldtype" : "Link",
    "label": "Project Manager Id",
    "options": "User",
    "hidden": "1"
  },
  {
    "fieldname" :"custom_bu_head",
    "fieldtype" : "Link",
    "label": "BU Head",
    "options": "Employee",
    "ignore_user_permissions": "1",
    "read_only": "1"
  },
  {
    "fetch_from": "custom_bu_head.user_id",
    "fieldname" :"custom_bu_head_id",
    "fieldtype" : "Link",
    "label": "BU Head Id",
    "options": "User",
    "hidden": "1"
  },
  {
    "fetch_from": "custom_purchase_manager.user_id",
    "fieldname" :"custom_purchase_manager",
    "fieldtype" : "Link",
    "label": "Purchase Manager",
    "options": "Employee",
    "ignore_user_permissions": "1",
    "read_only": "1"
  },
  {
    "fieldname" :"custom_purchase_manager_id",
    "fieldtype" : "Link",
    "label": "Purchase Manager Id",
    "options": "User",
    "hidden": "1"
  },
  {
    "fieldname" :"column_break_5",
    "fieldtype" : "Column Break",
    "print_width": "50%",
    "width": "50%"
  }
 ],
"index_web_pages_for_search": 1,
"is_submittable": 1,
"links": [],
"modified": "2025-03-17 17:23:10.339080",
"modified_by": "Administrator",
"module": "Utthunga Integrations",
"name": "Material Request",
"naming_rule": "Expression",
"owner": "Administrator",
"permissions": [
{
    "create": 1,
    "delete": 1,
    "email": 1,
    "export": 1,
    "print": 1,
    "read": 1,
    "report": 1,
    "role": "System Manager",
    "share": 1,
    "submit": 1,
    "write": 1
    }
],
"sort_field": "modified",
"sort_order": "DESC",
"states": []
}